Metadata-Version: 2.1
Name: stackboost
Version: 0.1.5
Summary: Stacked decision trees algorithm
Home-page: https://github.com/leffff/stackboost
Author: leffff
Author-email: levnovitskiy@gmail.com
License: MIT
Platform: UNKNOWN
Classifier: Programming Language :: Python :: 3
Classifier: Operating System :: OS Independent
Requires-Python: >=3.6
